lava/lib/peripherals/dvs/prophesee.py
lava/lib/peripherals/dvs/transformation.py
lava/lib/peripherals/liveplot/liveplot.py
lava/lib/peripherals/realsense/realsense.py
tests/__init__.py
tests/lava/__init__.py
tests/lava/lib/__init__.py
tests/lava/lib/peripherals/__init__.py
tests/lava/lib/peripherals/dvs/__init__.py
tests/lava/lib/peripherals/dvs/test_prophesee.py
tests/lava/lib/peripherals/dvs/test_transform.py
tests/lava/lib/peripherals/realsense/__init__.py
tests/lava/lib/peripherals/realsense/recording/bgr_1.png
tests/lava/lib/peripherals/realsense/recording/bgr_2.png
tests/lava/lib/peripherals/realsense/recording/depth_1.exr
tests/lava/lib/peripherals/realsense/recording/depth_2.exr
tests/lava/lib/peripherals/realsense/test_realsense.py
lava_peripherals-0.1.0.dist-info/LICENSE
lava_peripherals-0.1.0.dist-info/METADATA
lava_peripherals-0.1.0.dist-info/WHEEL
lava_peripherals-0.1.0.dist-info/RECORD
