Metadata-Version: 2.1
Name: lava-peripherals
Version: 0.1.0
Summary: A library that provides I/O processes for Lava such as DVS cameras and robotic actuators.
Home-page: https://lava-nc.org/
License: (BSD-3-Clause)
Keywords: neuromorphic,ai,artificial intelligence,neural models,dvs,realsense,robots,peripherals
Author: Intel's Neuromorphic Computing Lab and the open source community
Author-email: lava@intel.com
Requires-Python: >=3.8,<3.11
Classifier: Development Status :: 4 - Beta
Classifier: Intended Audience :: Science/Research
Classifier: License :: OSI Approved :: BSD License
Classifier: License :: Other/Proprietary License
Classifier: Operating System :: OS Independent
Classifier: Programming Language :: Python :: 3
Classifier: Programming Language :: Python :: 3.8
Classifier: Programming Language :: Python :: 3.9
Classifier: Programming Language :: Python :: 3.10
Classifier: Programming Language :: Python :: 3 :: Only
Classifier: Topic :: Scientific/Engineering :: Artificial Intelligence
Classifier: Topic :: Software Development :: Libraries :: Python Modules
Requires-Dist: fire (>=0.4.0,<0.5.0)
Requires-Dist: h5py (>=3.8.0,<4.0.0)
Requires-Dist: lava-nc (==0.9.0)
Requires-Dist: numba (>=0.57.0,<0.58.0)
Requires-Dist: numpy (>=1.23.0,<2.0.0)
Requires-Dist: opencv-python (>=4.5.5.64,<5.0.0.0)
Requires-Dist: pandas (>=2.0.2,<3.0.0)
Requires-Dist: pyrealsense2 (>=2.54.2.5684,<3.0.0.0)
Requires-Dist: scipy (>=1.10.0,<2.0.0)
Requires-Dist: sk-video (>=1.1.10,<2.0.0)
Project-URL: Discussions, https://github.com/lava-nc/lava-peripherals/discussions
Project-URL: Frequently Asked Questions, https://github.com/lava-nc/lava-peripherals/wiki/Frequently-Asked-Questions-(FAQ)
Project-URL: Issue and Bug Tracker, https://github.com/lava-nc/lava-peripherals/issues
Project-URL: Questions and Answers, https://github.com/lava-nc/lava-peripherals/discussions/categories/q-a
Project-URL: Repository, https://github.com/lava-nc/lava-peripherals.git
